dataproduct_mcp/server.py
dataproduct_mcp/connections/__init__.py
dataproduct_mcp/connections/bigquery_client.py
dataproduct_mcp/connections/databricks_client.py
dataproduct_mcp/connections/snowflake_client.py
dataproduct_mcp/datameshmanager/datamesh_manager_client.py
dataproduct_mcp/datameshmanager/models.py
dataproduct_mcp/guardrails/__init__.py
dataproduct_mcp/guardrails/prompt_injection.py
dataproduct_mcp/guardrails/readonly.py
mseep_dataproduct_mcp-0.1.12.dist-info/METADATA
mseep_dataproduct_mcp-0.1.12.dist-info/WHEEL
mseep_dataproduct_mcp-0.1.12.dist-info/entry_points.txt
mseep_dataproduct_mcp-0.1.12.dist-info/licenses/LICENSE
mseep_dataproduct_mcp-0.1.12.dist-info/RECORD
